chafa.py-1.2.0.dist-info/RECORD
chafa.py-1.2.0.dist-info/WHEEL
chafa.py-1.2.0.dist-info/METADATA
chafa.py-1.2.0.dist-info/licenses/COPYING.LESSER
chafa.py-1.2.0.dist-info/licenses/COPYING
chafa/term_info.py
chafa/enums.py
chafa/__init__.py
chafa/libraries.py
chafa/symbol_map.py
chafa/loader.py
chafa/frame.py
chafa/term_db.py
chafa/chafa.py
chafa/placement.py
chafa/canvas_config.py
chafa/image.py
chafa/canvas.py
chafa/.dylibs/libpcre2-8.0.dylib
chafa/.dylibs/libglib-2.0.0.dylib
chafa/.dylibs/libintl.8.dylib
chafa/libs/libchafa.dylib
