Metadata-Version: 2.3
Name: chafa.py
Version: 1.2.0
Summary: Python bindings for Chafa. Visualize images with text in python. 
Project-URL: Homepage, https://chafapy.mage.black
Project-URL: Source, https://github.com/guardkenzie/chafa.py
Project-URL: Bug Tracker, https://github.com/guardkenzie/chafa.py/issues
Author-email: Erica Ferrua Edwardsdóttir <e@mage.black>
License-Expression: LGPL-3.0
License-File: COPYING
License-File: COPYING.LESSER
Classifier: License :: OSI Approved :: GNU Lesser General Public License v3 (LGPLv3)
Classifier: Operating System :: MacOS
Classifier: Operating System :: Microsoft :: Windows
Classifier: Operating System :: Unix
Classifier: Programming Language :: Python :: 3
Requires-Python: >=3.8
